{"name":"forces","params":{"parts":{"_type":"dico","_default":{},"_dico":{"_type":"object","_default":0,"x":{"_type":"number","_default":0},"y":{"_type":"number","_default":0},"z":{"_type":"number","_default":0},"rotateX":{"_type":"number","_default":0},"rotateY":{"_type":"number","_default":0},"rotateZ":{"_type":"number","_default":0},"duration":{"_type":"number","_default":0},"elapsed":{"_type":"number","_default":0},"moved":{"_type":"object","_default":{"x":0,"y":0,"z":0,"rotateX":0,"rotateY":0,"rotateZ":0},"x":{"_type":"number","_default":0},"y":{"_type":"number","_default":0},"z":{"_type":"number","_default":0},"rotateX":{"_type":"number","_default":0},"rotateY":{"_type":"number","_default":0},"rotateZ":{"_type":"number","_default":0}},"easing":{"_type":"snippet","_default":{"scope":"demo","name":"ease-out"}},"handling":{"_type":"snippet","_default":false},"ending":{"_type":"snippet","_default":false}}}}}
